nb_service/__init__.py
nb_service/choices.py
nb_service/filtersets.py
nb_service/forms.py
nb_service/models.py
nb_service/navigation.py
nb_service/signals.py
nb_service/tables.py
nb_service/urls.py
nb_service/version.py
nb_service/views.py
nb_service/api/__init__.py
nb_service/api/serializers.py
nb_service/api/urls.py
nb_service/api/views.py
nb_service/migrations/0001_initial.py
nb_service/migrations/0002_application_custom_field_data_ic_custom_field_data_and_more.py
nb_service/migrations/0003_service_tags.py
nb_service/migrations/0004_alter_service_backup_profile.py
nb_service/migrations/0005_application_tags.py
nb_service/migrations/0006_ic_tags_pentest_tags_relation_tags.py
nb_service/migrations/__init__.py
nb_service/static/nb_service/export_svg.js
nb_service/static/nb_service/mermaid.min.js
nb_service/static/nb_service/mermaid.min.js.map
nb_service/templates/nb_service/application.html
nb_service/templates/nb_service/application_objs.html
nb_service/templates/nb_service/pentest.html
nb_service/templates/nb_service/relation.html
nb_service/templates/nb_service/service.html
nb_service/templates/nb_service/service_IC_view.html
nb_service/templates/nb_service/service_Relation_view.html
nb_service/templates/nb_service/service_diagram_view.html
nb_service/tests/__init__.py
nb_service/tests/custom.py
nb_service/tests/application/__init__.py
nb_service/tests/application/test_api.py
nb_service/tests/application/test_filters.py
nb_service/tests/application/test_views.py
nb_service/tests/service/__init__.py
nb_service/tests/service/test_api.py
nb_service/tests/service/test_filters.py
nb_service/tests/service/test_views.py
nb_service-4.2.0.dist-info/LICENSE
nb_service-4.2.0.dist-info/METADATA
nb_service-4.2.0.dist-info/WHEEL
nb_service-4.2.0.dist-info/top_level.txt
nb_service-4.2.0.dist-info/RECORD
