Metadata-Version: 2.1
Name: nb_service
Version: 4.2.0
Home-page: https://github.com/renatoalmeidaoliveira/nbservice
Author: Renato Almeida de Oliveira Zaroubin
Author-email: renato.almeida.oliveira@gmail.com
Classifier: Development Status :: 2 - Pre-Alpha
Classifier: Framework :: Django
Classifier: Programming Language :: Python :: 3
License-File: LICENSE
